model_evaluation/__init__.py
model_evaluation/evaluation.py
model_evaluation-0.0.0.dist-info/METADATA
model_evaluation-0.0.0.dist-info/WHEEL
model_evaluation-0.0.0.dist-info/top_level.txt
model_evaluation-0.0.0.dist-info/RECORD
